{
  "fetchedAt": "2026-04-04T19:05:42.271Z",
  "asx200": {
    "value": 8579.5,
    "change": -588,
    "changePercent": -6.41,
    "previousClose": 9167.5,
    "asOf": "2026-04-04",
    "history": [
      {
        "date": "2026-03-01",
        "close": 9167.5
      },
      {
        "date": "2026-03-02",
        "close": 9077.3
      },
      {
        "date": "2026-03-03",
        "close": 8901.2
      },
      {
        "date": "2026-03-04",
        "close": 8940.3
      },
      {
        "date": "2026-03-05",
        "close": 8851
      },
      {
        "date": "2026-03-08",
        "close": 8599
      },
      {
        "date": "2026-03-09",
        "close": 8692.6
      },
      {
        "date": "2026-03-10",
        "close": 8743.5
      },
      {
        "date": "2026-03-11",
        "close": 8629
      },
      {
        "date": "2026-03-12",
        "close": 8617.1
      },
      {
        "date": "2026-03-15",
        "close": 8583.4
      },
      {
        "date": "2026-03-16",
        "close": 8614.3
      },
      {
        "date": "2026-03-17",
        "close": 8640.6
      },
      {
        "date": "2026-03-18",
        "close": 8497.8
      },
      {
        "date": "2026-03-19",
        "close": 8428.4
      },
      {
        "date": "2026-03-22",
        "close": 8365.9
      },
      {
        "date": "2026-03-23",
        "close": 8379.4
      },
      {
        "date": "2026-03-24",
        "close": 8557.6
      },
      {
        "date": "2026-03-25",
        "close": 8525.7
      },
      {
        "date": "2026-03-26",
        "close": 8516.3
      },
      {
        "date": "2026-03-29",
        "close": 8461
      },
      {
        "date": "2026-03-30",
        "close": 8481.8
      },
      {
        "date": "2026-03-31",
        "close": 8671.8
      },
      {
        "date": "2026-04-01",
        "close": 8579.5
      },
      {
        "date": "2026-04-02",
        "close": 8579.5
      }
    ]
  },
  "audusd": {
    "value": 0.69,
    "change": -0.02,
    "changePercent": -3.03,
    "previousClose": 0.71,
    "asOf": "2026-04-04",
    "history": [
      {
        "date": "2026-03-03",
        "close": 0.71
      },
      {
        "date": "2026-03-04",
        "close": 0.7
      },
      {
        "date": "2026-03-05",
        "close": 0.71
      },
      {
        "date": "2026-03-06",
        "close": 0.7
      },
      {
        "date": "2026-03-09",
        "close": 0.7
      },
      {
        "date": "2026-03-10",
        "close": 0.71
      },
      {
        "date": "2026-03-11",
        "close": 0.71
      },
      {
        "date": "2026-03-12",
        "close": 0.71
      },
      {
        "date": "2026-03-13",
        "close": 0.71
      },
      {
        "date": "2026-03-16",
        "close": 0.7
      },
      {
        "date": "2026-03-17",
        "close": 0.71
      },
      {
        "date": "2026-03-18",
        "close": 0.71
      },
      {
        "date": "2026-03-19",
        "close": 0.7
      },
      {
        "date": "2026-03-20",
        "close": 0.71
      },
      {
        "date": "2026-03-23",
        "close": 0.7
      },
      {
        "date": "2026-03-24",
        "close": 0.7
      },
      {
        "date": "2026-03-25",
        "close": 0.7
      },
      {
        "date": "2026-03-26",
        "close": 0.69
      },
      {
        "date": "2026-03-27",
        "close": 0.69
      },
      {
        "date": "2026-03-29",
        "close": 0.69
      },
      {
        "date": "2026-03-30",
        "close": 0.68
      },
      {
        "date": "2026-03-31",
        "close": 0.69
      },
      {
        "date": "2026-04-01",
        "close": 0.69
      },
      {
        "date": "2026-04-02",
        "close": 0.69
      },
      {
        "date": "2026-04-04",
        "close": 0.69
      }
    ]
  },
  "commodities": [
    {
      "name": "Gold",
      "icon": "🥇",
      "iconBg": "#fef9ee",
      "price": 4702.7,
      "change": -591.7,
      "changePercent": -11.18
    },
    {
      "name": "Silver",
      "icon": "🥈",
      "iconBg": "#f8f9fa",
      "price": 73.17,
      "change": -15.11,
      "changePercent": -17.12
    },
    {
      "name": "Crude Oil (WTI)",
      "icon": "🛢️",
      "iconBg": "#f3f0f9",
      "price": 112.06,
      "change": 40.83,
      "changePercent": 57.32
    },
    {
      "name": "Copper",
      "icon": "🔶",
      "iconBg": "#fef0e6",
      "price": 5.68,
      "change": -0.21,
      "changePercent": -3.61
    },
    {
      "name": "BHP Group",
      "icon": "⛏️",
      "iconBg": "#e6f2ec",
      "price": 51.23,
      "change": -8.02,
      "changePercent": -13.54
    },
    {
      "name": "Rio Tinto",
      "icon": "🏗️",
      "iconBg": "#eff6ff",
      "price": 161.62,
      "change": -7.82,
      "changePercent": -4.62
    }
  ],
  "sectors": [
    {
      "name": "Financials",
      "changePercent": 0.11,
      "stocks": [
        {
          "name": "CBA",
          "price": 172.8,
          "changePercent": 0.52
        },
        {
          "name": "WBC",
          "price": 39.85,
          "changePercent": -0.52
        },
        {
          "name": "ANZ",
          "price": 36.63,
          "changePercent": 0.71
        },
        {
          "name": "NAB",
          "price": 41.8,
          "changePercent": -0.29
        }
      ]
    },
    {
      "name": "Materials",
      "changePercent": -4.09,
      "stocks": [
        {
          "name": "BHP",
          "price": 51.23,
          "changePercent": -2.53
        },
        {
          "name": "RIO",
          "price": 161.62,
          "changePercent": -3.27
        },
        {
          "name": "FMG",
          "price": 20.25,
          "changePercent": -3.98
        },
        {
          "name": "MIN",
          "price": 52.68,
          "changePercent": -6.58
        }
      ]
    },
    {
      "name": "Health Care",
      "changePercent": -1.83,
      "stocks": [
        {
          "name": "CSL",
          "price": 138.93,
          "changePercent": -2.28
        },
        {
          "name": "COH",
          "price": 172.36,
          "changePercent": -1.53
        },
        {
          "name": "RMD",
          "price": 32.21,
          "changePercent": -1.59
        },
        {
          "name": "SHL",
          "price": 19.98,
          "changePercent": -1.91
        }
      ]
    },
    {
      "name": "Consumer Discretionary",
      "changePercent": -1.49,
      "stocks": [
        {
          "name": "WES",
          "price": 73.34,
          "changePercent": -0.12
        },
        {
          "name": "HVN",
          "price": 4.73,
          "changePercent": -2.87
        },
        {
          "name": "JBH",
          "price": 72.05,
          "changePercent": -1.84
        },
        {
          "name": "ALL",
          "price": 46.15,
          "changePercent": -1.14
        }
      ]
    },
    {
      "name": "Industrials",
      "changePercent": -0.4,
      "stocks": [
        {
          "name": "TCL",
          "price": 13.86,
          "changePercent": 0.14
        },
        {
          "name": "BXB",
          "price": 22.83,
          "changePercent": -0.35
        },
        {
          "name": "SYD",
          "price": 0,
          "changePercent": 0
        },
        {
          "name": "QAN",
          "price": 8.55,
          "changePercent": -1.38
        }
      ]
    },
    {
      "name": "Real Estate",
      "changePercent": -1.28,
      "stocks": [
        {
          "name": "GMG",
          "price": 26.08,
          "changePercent": -0.19
        },
        {
          "name": "SGP",
          "price": 4.12,
          "changePercent": -2.83
        },
        {
          "name": "GPT",
          "price": 4.45,
          "changePercent": -0.67
        },
        {
          "name": "MGR",
          "price": 1.71,
          "changePercent": -1.45
        }
      ]
    },
    {
      "name": "Consumer Staples",
      "changePercent": 0.9,
      "stocks": [
        {
          "name": "WOW",
          "price": 37.01,
          "changePercent": 1.26
        },
        {
          "name": "COL",
          "price": 22.62,
          "changePercent": 2.59
        },
        {
          "name": "TWE",
          "price": 3.73,
          "changePercent": -0.8
        },
        {
          "name": "A2M",
          "price": 9.39,
          "changePercent": 0.54
        }
      ]
    },
    {
      "name": "Energy",
      "changePercent": 0.14,
      "stocks": [
        {
          "name": "WDS",
          "price": 34.93,
          "changePercent": -0.46
        },
        {
          "name": "STO",
          "price": 8.08,
          "changePercent": 1.38
        },
        {
          "name": "ORG",
          "price": 12.59,
          "changePercent": 1.37
        },
        {
          "name": "WHC",
          "price": 9.08,
          "changePercent": -1.73
        }
      ]
    },
    {
      "name": "Information Technology",
      "changePercent": -3.05,
      "stocks": [
        {
          "name": "XRO",
          "price": 74.06,
          "changePercent": -3.81
        },
        {
          "name": "WTC",
          "price": 37.88,
          "changePercent": -4.3
        },
        {
          "name": "CPU",
          "price": 28.33,
          "changePercent": -1.63
        },
        {
          "name": "APX",
          "price": 1.39,
          "changePercent": -2.46
        }
      ]
    },
    {
      "name": "Communication Services",
      "changePercent": -2.38,
      "stocks": [
        {
          "name": "TLS",
          "price": 5.42,
          "changePercent": 1.5
        },
        {
          "name": "REA",
          "price": 154.41,
          "changePercent": -3.66
        },
        {
          "name": "CAR",
          "price": 22.54,
          "changePercent": -3.63
        },
        {
          "name": "NWS",
          "price": 40.6,
          "changePercent": -3.75
        }
      ]
    },
    {
      "name": "Utilities",
      "changePercent": -0.21,
      "stocks": [
        {
          "name": "AGL",
          "price": 9.92,
          "changePercent": 0
        },
        {
          "name": "APA",
          "price": 9.86,
          "changePercent": 0.61
        },
        {
          "name": "ORG",
          "price": 12.59,
          "changePercent": 1.37
        },
        {
          "name": "MEZ",
          "price": 4.47,
          "changePercent": -2.83
        }
      ]
    }
  ],
  "rbaRate": {
    "value": 4.1,
    "change": 0,
    "asOf": "2025-02-18",
    "note": "RBA Official Cash Rate Target"
  },
  "cpi": {
    "value": 2.4,
    "change": -0.5,
    "period": "Q4 2024",
    "note": "ABS Consumer Price Index, annual change"
  },
  "gdp": {
    "value": 1.5,
    "change": 0.3,
    "period": "Q3 2024",
    "note": "ABS GDP annual growth"
  },
  "unemployment": {
    "value": 4.1,
    "change": 0.1,
    "period": "Jan 2025",
    "note": "ABS Labour Force"
  },
  "housing": {
    "medianPrice": 1182000,
    "changePercent": 4.7,
    "city": "Sydney (Median House)",
    "note": "CoreLogic Home Value Index",
    "cities": [
      {
        "city": "Sydney",
        "median": 1182000,
        "changePercent": 4.7,
        "rentalYield": 2.8,
        "auctionClearance": 68,
        "priceToIncome": 13.2,
        "daysOnMarket": 28
      },
      {
        "city": "Melbourne",
        "median": 935000,
        "changePercent": 1.2,
        "rentalYield": 3.1,
        "auctionClearance": 62,
        "priceToIncome": 10.5,
        "daysOnMarket": 33
      },
      {
        "city": "Brisbane",
        "median": 872000,
        "changePercent": 11.8,
        "rentalYield": 3.6,
        "auctionClearance": 55,
        "priceToIncome": 8.9,
        "daysOnMarket": 22
      },
      {
        "city": "Perth",
        "median": 785000,
        "changePercent": 18.4,
        "rentalYield": 4.2,
        "auctionClearance": 48,
        "priceToIncome": 7.1,
        "daysOnMarket": 18
      },
      {
        "city": "Adelaide",
        "median": 762000,
        "changePercent": 14.3,
        "rentalYield": 3.8,
        "auctionClearance": 72,
        "priceToIncome": 8.2,
        "daysOnMarket": 24
      },
      {
        "city": "Hobart",
        "median": 668000,
        "changePercent": -0.8,
        "rentalYield": 4,
        "auctionClearance": 45,
        "priceToIncome": 9.1,
        "daysOnMarket": 38
      },
      {
        "city": "Canberra",
        "median": 955000,
        "changePercent": 1.5,
        "rentalYield": 3.4,
        "auctionClearance": 58,
        "priceToIncome": 7.8,
        "daysOnMarket": 31
      },
      {
        "city": "Darwin",
        "median": 530000,
        "changePercent": 2.1,
        "rentalYield": 5.8,
        "auctionClearance": 38,
        "priceToIncome": 5.4,
        "daysOnMarket": 42
      }
    ]
  },
  "consumerConfidence": {
    "value": 92.2,
    "change": 1,
    "period": "Feb 2025",
    "note": "Westpac-Melbourne Institute Consumer Sentiment"
  },
  "rbaHistory": [
    {
      "date": "Feb 2025",
      "rate": 4.1,
      "change": -0.25,
      "note": "First cut since Nov 2020 — CPI back within 2–3% target band"
    },
    {
      "date": "Dec 2024",
      "rate": 4.35,
      "change": 0,
      "note": "Held steady; board noted disinflation progressing"
    },
    {
      "date": "Nov 2024",
      "rate": 4.35,
      "change": 0,
      "note": "Held; trimmed mean CPI still above target"
    },
    {
      "date": "Sep 2024",
      "rate": 4.35,
      "change": 0,
      "note": "Held; watching services inflation persistence"
    },
    {
      "date": "Aug 2024",
      "rate": 4.35,
      "change": 0,
      "note": "Held; acknowledged slowing growth"
    },
    {
      "date": "Jun 2024",
      "rate": 4.35,
      "change": 0,
      "note": "Held; inflation sticky but rate hike ruled out"
    },
    {
      "date": "May 2024",
      "rate": 4.35,
      "change": 0,
      "note": "Held; CPI surprised to upside in Q1"
    },
    {
      "date": "Mar 2024",
      "rate": 4.35,
      "change": 0,
      "note": "Held; easing bias introduced"
    },
    {
      "date": "Feb 2024",
      "rate": 4.35,
      "change": 0,
      "note": "Held; inflation declining but not fast enough"
    },
    {
      "date": "Nov 2023",
      "rate": 4.35,
      "change": 0.25,
      "note": "Final hike of cycle; CPI re-accelerated in Q3"
    }
  ],
  "indicators": [
    {
      "name": "GDP Growth (Annual)",
      "value": "1.5%",
      "previous": "1.2%",
      "change": 0.3,
      "unit": "%",
      "period": "Q3 2024",
      "category": "growth"
    },
    {
      "name": "GDP Growth (Quarterly)",
      "value": "0.3%",
      "previous": "0.2%",
      "change": 0.1,
      "unit": "%",
      "period": "Q3 2024",
      "category": "growth"
    },
    {
      "name": "CPI Inflation (Annual)",
      "value": "2.4%",
      "previous": "2.9%",
      "change": -0.5,
      "unit": "%",
      "period": "Q4 2024",
      "category": "prices"
    },
    {
      "name": "Trimmed Mean CPI",
      "value": "3.2%",
      "previous": "3.5%",
      "change": -0.3,
      "unit": "%",
      "period": "Q4 2024",
      "category": "prices"
    },
    {
      "name": "RBA Cash Rate",
      "value": "4.10%",
      "previous": "4.35%",
      "change": -0.25,
      "unit": "%",
      "period": "Feb 2025",
      "category": "prices"
    },
    {
      "name": "Unemployment Rate",
      "value": "4.1%",
      "previous": "4.0%",
      "change": 0.1,
      "unit": "%",
      "period": "Jan 2025",
      "category": "labour"
    },
    {
      "name": "Participation Rate",
      "value": "67.2%",
      "previous": "67.1%",
      "change": 0.1,
      "unit": "%",
      "period": "Jan 2025",
      "category": "labour"
    },
    {
      "name": "Wage Price Index (Annual)",
      "value": "3.5%",
      "previous": "4.1%",
      "change": -0.6,
      "unit": "%",
      "period": "Q3 2024",
      "category": "labour"
    },
    {
      "name": "Trade Balance",
      "value": "A$5.9B",
      "previous": "A$4.6B",
      "change": 1.3,
      "unit": "B",
      "period": "Dec 2024",
      "category": "trade"
    },
    {
      "name": "Retail Sales (Monthly)",
      "value": "0.1%",
      "previous": "0.5%",
      "change": -0.4,
      "unit": "%",
      "period": "Dec 2024",
      "category": "growth"
    },
    {
      "name": "Building Approvals",
      "value": "-0.3%",
      "previous": "5.0%",
      "change": -5.3,
      "unit": "%",
      "period": "Dec 2024",
      "category": "growth"
    },
    {
      "name": "Consumer Sentiment",
      "value": "92.2",
      "previous": "91.2",
      "change": 1,
      "unit": "",
      "period": "Feb 2025",
      "category": "growth"
    },
    {
      "name": "Business Confidence (NAB)",
      "value": "4",
      "previous": "2",
      "change": 2,
      "unit": "",
      "period": "Jan 2025",
      "category": "growth"
    },
    {
      "name": "PMI Manufacturing",
      "value": "50.2",
      "previous": "49.4",
      "change": 0.8,
      "unit": "",
      "period": "Feb 2025",
      "category": "growth"
    }
  ],
  "news": [
    {
      "title": "Cotton-Davis rivalry has gone global, 36ers coach says ahead of decider",
      "link": "https://www.abc.net.au/news/2026-04-04/nbl-championship-getting-global-attention-36ers-coach-says/106531442",
      "snippet": "",
      "pubDate": "Sat, 04 Apr 2026 06:29:11 +0000",
      "source": "ABC News"
    },
    {
      "title": "Watch as the Olympic silver medallist destroys the Stawell Gift field",
      "link": "https://www.abc.net.au/news/2026-04-04/shacarri-richardson-christian-coleman-stawell-gift-heats/106531620",
      "snippet": "",
      "pubDate": "Sat, 04 Apr 2026 06:26:31 +0000",
      "source": "ABC News"
    },
    {
      "title": "Flanagan apologises to fans following Dragons horror show",
      "link": "https://www.abc.net.au/news/2026-04-04/nrl-dragons-cowboys-broncos-titans-flanagan-walsh/106531642",
      "snippet": "",
      "pubDate": "Sat, 04 Apr 2026 06:18:43 +0000",
      "source": "ABC News"
    },
    {
      "title": "Swans complete huge win over Eagles as Heeney stars on return",
      "link": "https://www.abc.net.au/news/2026-04-04/swans-thump-eagles-port-down-tigers/106530538",
      "snippet": "",
      "pubDate": "Sat, 04 Apr 2026 04:48:30 +0000",
      "source": "ABC News"
    },
    {
      "title": "Rising star among 3 Australians picked in WNBA expansion draft",
      "link": "https://www.abc.net.au/news/2026-04-04/nyadiew-puoch-chloe-bibby-kristy-wallace-in-wnba-expansion-draft/106531434",
      "snippet": "",
      "pubDate": "Sat, 04 Apr 2026 02:26:50 +0000",
      "source": "ABC News"
    },
    {
      "title": "Why Stuart isn't alarmed by Raiders' poor start to NRL season",
      "link": "https://www.abc.net.au/news/2026-04-04/nrl-canberra-raiders-ricky-stuart-newcastle-knights/106531370",
      "snippet": "",
      "pubDate": "Sat, 04 Apr 2026 01:05:29 +0000",
      "source": "ABC News"
    },
    {
      "title": "'Adrenaline rush' of adaptive skateboarding redefines inclusive sport",
      "link": "https://www.abc.net.au/news/2026-04-04/adaptive-skateboarding-opens-doors-for-people-with-disability/106515066",
      "snippet": "",
      "pubDate": "Sat, 04 Apr 2026 00:38:14 +0000",
      "source": "ABC News"
    },
    {
      "title": "Lakers lose 'MVP candidate' to injury as NBA play-offs approach",
      "link": "https://www.abc.net.au/news/2026-04-04/nba-los-angeles-lakers-lose-luka-doncic-to-injury/106531272",
      "snippet": "",
      "pubDate": "Fri, 03 Apr 2026 23:35:08 +0000",
      "source": "ABC News"
    },
    {
      "title": "Demons star praised for reaching 'another level' with career-best form",
      "link": "https://www.abc.net.au/news/2026-04-04/afl-kysaiah-pickett-melbourne-demons-gold-coast-suns/106531202",
      "snippet": "",
      "pubDate": "Fri, 03 Apr 2026 21:55:36 +0000",
      "source": "ABC News"
    },
    {
      "title": "How a rising teen star is making a name for himself in Aussie athletics",
      "link": "https://www.abc.net.au/news/2026-04-04/australian-athletics-800-metres-daniel-williams/106521032",
      "snippet": "",
      "pubDate": "Fri, 03 Apr 2026 21:45:12 +0000",
      "source": "ABC News"
    },
    {
      "title": "Apple’s 50-year history has redefined technology, culture and comebacks",
      "link": "https://www.smh.com.au/business/companies/apple-s-50-year-history-has-redefined-technology-culture-and-comebacks-20260402-p5zktc.html?ref=rss&amp;utm_medium=rss&amp;utm_source=rss_business",
      "snippet": "An improbable odyssey began on April Fools’ Day five decades ago, when Steve Jobs and Steve Wozniak signed a two-page document that created Apple Computer Co.",
      "pubDate": "Sat, 04 Apr 2026 07:00:00 +1100",
      "source": "SMH Business"
    },
    {
      "title": "Australians hate surcharges. So why don’t we move to QR codes?",
      "link": "https://www.smh.com.au/business/the-economy/australians-hate-surcharges-so-why-don-t-we-move-to-qr-codes-20260402-p5zkvl.html?ref=rss&amp;utm_medium=rss&amp;utm_source=rss_business",
      "snippet": "It’s a payment method that has taken off in cash-loving Japan. But here’s why Australians will still pay more to use card.",
      "pubDate": "Sat, 04 Apr 2026 06:00:00 +1100",
      "source": "SMH Business"
    }
  ]
}